gautomatch/__init__.py
gautomatch/bibtex.py
gautomatch/constants.py
gautomatch/convert.py
gautomatch/protocols.conf
gautomatch/run_gautomatch.py
gautomatch/viewers.py
gautomatch/wizards.py
gautomatch/protocols/__init__.py
gautomatch/protocols/protocol_gautomatch.py
gautomatch/tests/__init__.py
gautomatch/tests/test_protocols_gautomatch.py
scipion_em_gautomatch-3.2.1.dist-info/LICENSE
scipion_em_gautomatch-3.2.1.dist-info/METADATA
scipion_em_gautomatch-3.2.1.dist-info/WHEEL
scipion_em_gautomatch-3.2.1.dist-info/entry_points.txt
scipion_em_gautomatch-3.2.1.dist-info/top_level.txt
scipion_em_gautomatch-3.2.1.dist-info/RECORD
